sparsepca.py
sparsepca-0.2.3.dist-info/LICENSE
sparsepca-0.2.3.dist-info/METADATA
sparsepca-0.2.3.dist-info/WHEEL
sparsepca-0.2.3.dist-info/top_level.txt
sparsepca-0.2.3.dist-info/RECORD
