Metadata-Version: 2.1
Name: sparsepca
Version: 0.2.3
Summary: Sparse Principal Component Analysis in Python
Home-page: UNKNOWN
Author: Shixiang Chen, Justin Huang, Benjamin Jochem, Shiqian Ma, Lingzhou Xue, and Hui Zou
Author-email: lzxue@psu.edu
License: MIT
Project-URL: Documentation, https://xinging-birds.github.io/AManPG/
Project-URL: Source, https://github.com/xinging-birds/AManPG
Platform: UNKNOWN
Classifier: Development Status :: 4 - Beta
Classifier: Programming Language :: Python :: 3
Classifier: Programming Language :: Python :: 3.8
Classifier: Programming Language :: Python :: 3.9
Classifier: License :: OSI Approved :: MIT License
Classifier: Operating System :: OS Independent
Requires-Python: >=3.8
License-File: LICENSE
Requires-Dist: numpy
